{
    "JD": {
        "assetMainType": "EQUITY",
        "assetSubType": "ADR",
        "quoteType": "NBBO",
        "realtime": true,
        "ssid": 1968918838,
        "symbol": "JD",
        "extended": {
            "askPrice": 0.0,
            "askSize": 0,
            "bidPrice": 0.0,
            "bidSize": 0,
            "lastPrice": 33.48,
            "lastSize": 100,
            "mark": 0.0,
            "quoteTime": 1748505600000,
            "totalVolume": 0,
            "tradeTime": 1748505473000
        },
        "fundamental": {
            "avg10DaysVolume": 14282609.0,
            "avg1YearVolume": 14048304.0,
            "declarationDate": "2025-03-06T00:00:00Z",
            "divAmount": 1.0,
            "divExDate": "2025-04-08T00:00:00Z",
            "divFreq": 1,
            "divPayAmount": 0.98,
            "divPayDate": "2025-04-29T00:00:00Z",
            "divYield": 3.16656,
            "eps": 3.67973,
            "fundLeverageFactor": 0.0,
            "lastEarningsDate": "2025-05-13T00:00:00Z",
            "nextDivExDate": "2026-04-08T00:00:00Z",
            "nextDivPayDate": "2026-04-29T00:00:00Z",
            "peRatio": 7.75493
        },
        "quote": {
            "52WeekHigh": 47.82,
            "52WeekLow": 24.13,
            "askMICId": "ARCX",
            "askPrice": 32.99,
            "askSize": 2,
            "askTime": 1748554859975,
            "bidMICId": "EDGX",
            "bidPrice": 32.91,
            "bidSize": 1,
            "bidTime": 1748554925975,
            "closePrice": 31.58,
            "highPrice": 33.12,
            "lastMICId": "XADF",
            "lastPrice": 32.91,
            "lastSize": 700,
            "lowPrice": 32.525,
            "mark": 32.94,
            "markChange": 1.36,
            "markPercentChange": 4.30652312,
            "netChange": 1.33,
            "netPercentChange": 4.21152628,
            "openPrice": 32.99,
            "postMarketChange": -0.03,
            "postMarketPercentChange": -0.09107468,
            "quoteTime": 1748554925975,
            "securityStatus": "Normal",
            "totalVolume": 18241804,
            "tradeTime": 1748554982170
        },
        "reference": {
            "cusip": "47215P106",
            "description": "JD COM INC A ADR",
            "exchange": "Q",
            "exchangeName": "NASDAQ",
            "isHardToBorrow": false,
            "isShortable": true,
            "htbQuantity": 2157322,
            "htbRate": 0.0
        },
        "regular": {
            "regularMarketLastPrice": 32.94,
            "regularMarketLastSize": 258554,
            "regularMarketNetChange": 1.36,
            "regularMarketPercentChange": 4.30652312,
            "regularMarketTradeTime": 1748548800329
        }
    }
}