{
    "XOM": {
        "assetMainType": "EQUITY",
        "assetSubType": "COE",
        "quoteType": "NBBO",
        "realtime": true,
        "ssid": 690762788,
        "symbol": "XOM",
        "extended": {
            "askPrice": 0.0,
            "askSize": 0,
            "bidPrice": 0.0,
            "bidSize": 0,
            "lastPrice": 103.0,
            "lastSize": 9,
            "mark": 0.0,
            "quoteTime": 1748505600000,
            "totalVolume": 0,
            "tradeTime": 1748503557000
        },
        "fundamental": {
            "avg10DaysVolume": 14236330.0,
            "avg1YearVolume": 15549674.0,
            "declarationDate": "2025-05-02T00:00:00Z",
            "divAmount": 3.96,
            "divExDate": "2025-05-15T00:00:00Z",
            "divFreq": 4,
            "divPayAmount": 0.99,
            "divPayDate": "2025-06-10T00:00:00Z",
            "divYield": 3.82535,
            "eps": 7.8362,
            "fundLeverageFactor": 0.0,
            "lastEarningsDate": "2025-05-02T00:00:00Z",
            "nextDivExDate": "2025-08-15T00:00:00Z",
            "nextDivPayDate": "2025-09-10T00:00:00Z",
            "peRatio": 13.52477
        },
        "quote": {
            "52WeekHigh": 126.34,
            "52WeekLow": 97.8,
            "askMICId": "XNAS",
            "askPrice": 102.69,
            "askSize": 1,
            "askTime": 1748553828899,
            "bidMICId": "EDGX",
            "bidPrice": 102.5,
            "bidSize": 1,
            "bidTime": 1748552940001,
            "closePrice": 102.11,
            "highPrice": 102.845,
            "lastMICId": "XADF",
            "lastPrice": 102.6874,
            "lastSize": 360,
            "lowPrice": 101.75,
            "mark": 102.69,
            "markChange": 0.58,
            "markPercentChange": 0.56801489,
            "netChange": 0.5774,
            "netPercentChange": 0.56546861,
            "openPrice": 102.28,
            "postMarketChange": -0.0026,
            "postMarketPercentChange": -0.00253189,
            "quoteTime": 1748553828899,
            "securityStatus": "Normal",
            "totalVolume": 13824863,
            "tradeTime": 1748555027662
        },
        "reference": {
            "cusip": "30231G102",
            "description": "EXXON MOBIL CORP",
            "exchange": "N",
            "exchangeName": "NYSE",
            "isHardToBorrow": false,
            "isShortable": true,
            "htbQuantity": 4144104,
            "htbRate": 0.0
        },
        "regular": {
            "regularMarketLastPrice": 102.69,
            "regularMarketLastSize": 1655456,
            "regularMarketNetChange": 0.58,
            "regularMarketPercentChange": 0.56801489,
            "regularMarketTradeTime": 1748549400001
        }
    }
}